<?xml version="1.0" encoding="UTF-8"?>
<actions>
<action>
	<icon>utilities-terminal</icon>
	<name>Open Terminal Here</name>
	<unique-id>1638248679590500-1</unique-id>
	<command>sh -c 'cd %f;st'</command>
	<description>Example for a custom action</description>
	<patterns>*</patterns>
	<startup-notify/>
	<directories/>
</action>
<action>
	<icon>utilities-terminal</icon>
	<name>Open Root Terminal Here</name>
	<unique-id>1638248679590500-1</unique-id>
	<command>sh -c 'cd %f;gksudo st'</command>
	<description>Example for a custom action</description>
	<patterns>*</patterns>
	<startup-notify/>
	<directories/>
</action>
</actions>
